LICENSE
zen_dash/__init__.py
zen_dash/auth/__init__.py
zen_dash/cli/__init__.py
zen_dash/cli/main.py
zen_dash/cli/project_management.py
zen_dash/flex_data.py
zen_dash/instances.py
zen_dash/objects/__init__.py
zen_dash/objects/flex_data.py
zen_dash/objects/instances.py
zen_dash/objects/page.py
zen_dash/objects/scripts.py
zen_dash/objects/sidebar.py
zen_dash/page.py
zen_dash/route.py
zen_dash/scripts.py
zen_dash/sidebar.py
zen_dash/static/275.44cd52f9d992445f.js
zen_dash/static/3rdpartylicenses.txt
zen_dash/static/MaterialIcons-Regular.196fa4a92dd6fa73.ttf
zen_dash/static/MaterialIcons-Regular.1e50f5c2ffa6aba4.eot
zen_dash/static/MaterialIcons-Regular.7ea2023eeca07427.woff2
zen_dash/static/MaterialIcons-Regular.db852539204b1a34.woff
zen_dash/static/favicon.ico
zen_dash/static/index.html
zen_dash/static/main.ee1151fcb00e6f66.js
zen_dash/static/polyfills.0a8881ff36766b1e.js
zen_dash/static/runtime.6a9b461ae5a72237.js
zen_dash/static/styles.362a8260c32d36d9.css
zen_dash/static/vendor.58b0316441ec254e.js
zen_dash/support/__init__.py
zen_dash/support/encoder.py
zen_dash/tag/__init__.py
zen_dash/websocket/__init__.py
zen_dash-0.6.27.dist-info/LICENSE
zen_dash-0.6.27.dist-info/METADATA
zen_dash-0.6.27.dist-info/WHEEL
zen_dash-0.6.27.dist-info/entry_points.txt
zen_dash-0.6.27.dist-info/RECORD
