Metadata-Version: 2.1
Name: zen_dash
Version: 0.6.27
Summary: Simple yet scable and production ready python dashboard that is better than shiny application for business.
Home-page: https://zen-reportz.github.io/zen_dash/index.html
License: MIT
Author: Zen
Author-email: zenreportz@pm.me
Requires-Python: >=3.12,<4.0
Classifier: License :: OSI Approved :: MIT License
Classifier: Programming Language :: Python :: 3
Classifier: Programming Language :: Python :: 3.12
Requires-Dist: Jinja2 (>=3.1.1,<4.0.0)
Requires-Dist: click (>=8.1.3,<9.0.0)
Requires-Dist: fastapi (>=0.92.0,<0.93.0)
Requires-Dist: python-jose[cryptography] (>=3.3.0,<4.0.0)
Requires-Dist: python-multipart (>=0.0.5,<0.0.6)
Requires-Dist: sphinx-rtd-theme (>=1.0.0,<2.0.0)
Requires-Dist: websocket (>=0.2.1,<0.3.0)
Requires-Dist: websockets (>=10.4,<11.0)
Project-URL: Repository, https://github.com/Zen-Reportz/zen_dash
